{
  "database_name": "ecommerce_db",
  "description": "پایگاه داده فروشگاه آنلاین با اطلاعات مشتریان، محصولات و خریدها",
  "tables": [
    {
      "name": "Customers",
      "description": "اطلاعات مشتریان شامل نام، تاریخ عضویت و شهر محل سکونت",
      "key_columns": ["CustomerID", "Name", "JoinDate", "City"],
      "business_role": "نگهداری مشخصات اشخاصی که در فروشگاه ثبت‌نام کرده و خرید انجام داده‌اند"
    },
    {
      "name": "Products",
      "description": "اطلاعات محصولات موجود در فروشگاه شامل نام، قیمت و دسته‌بندی",
      "key_columns": ["ProductID", "ProductName", "Price", "Category"],
      "business_role": "نگهداری کالاها و خدماتی که در فروشگاه برای فروش عرضه می‌شوند"
    },
    {
      "name": "Purchases",
      "description": "ثبت سوابق خریدهای انجام شده توسط مشتریان",
      "key_columns": ["PurchaseID", "CustomerID", "ProductID", "PurchaseDate", "PurchaseAmount", "Quantity"],
      "business_role": "ثبت تراکنش‌های خرید شامل مبلغ، تاریخ و تعداد کالای خریداری شده"
    },
    {
      "name": "Orders",
      "description": "اطلاعات سفارشات ثبت شده قبل از پرداخت",
      "key_columns": ["OrderID", "CustomerID", "OrderDate", "Status", "TotalAmount"],
      "business_role": "مدیریت سفارشات مشتریان در مراحل مختلف از ثبت تا تحویل"
    }
  ],
  "columns": [
    {
      "table_name": "Customers",
      "column_name": "CustomerID",
      "meaning": "شناسه یکتای مشتری به عنوان کلید اصلی",
      "data_type": "integer",
      "operations": "شناسایی مشتری و ارتباط با جداول خرید و سفارش"
    },
    {
      "table_name": "Customers",
      "column_name": "Name",
      "meaning": "نام و نام خانوادگی مشتری",
      "data_type": "varchar",
      "operations": "نمایش و جستجوی اطلاعات مشتری بر اساس نام"
    },
    {
      "table_name": "Customers",
      "column_name": "JoinDate",
      "meaning": "تاریخ عضویت مشتری در سامانه",
      "data_type": "date",
      "operations": "فیلتر کردن مشتریان بر اساس بازه زمانی عضویت و محاسبه قدمت مشتری"
    },
    {
      "table_name": "Customers",
      "column_name": "City",
      "meaning": "شهر محل سکونت مشتری",
      "data_type": "varchar",
      "operations": "تجزیه و تحلیل جغرافیایی مشتریان و گزارش‌گیری بر اساس منطقه"
    },
    {
      "table_name": "Products",
      "column_name": "ProductID",
      "meaning": "شناسه یکتای محصول به عنوان کلید اصلی",
      "data_type": "integer",
      "operations": "شناسایی محصول و ارتباط با جدول خریدها"
    },
    {
      "table_name": "Products",
      "column_name": "ProductName",
      "meaning": "نام محصول",
      "data_type": "varchar",
      "operations": "نمایش و جستجوی محصولات"
    },
    {
      "table_name": "Products",
      "column_name": "Price",
      "meaning": "قیمت واحد محصول به تومان",
      "data_type": "decimal",
      "operations": "محاسبه مبلغ کل خرید و فیلتر کردن بر اساس قیمت"
    },
    {
      "table_name": "Products",
      "column_name": "Category",
      "meaning": "دسته‌بندی محصول مانند الکترونیک، پوشاک، کتاب",
      "data_type": "varchar",
      "operations": "گروه‌بندی و فیلتر محصولات بر اساس دسته"
    },
    {
      "table_name": "Purchases",
      "column_name": "PurchaseID",
      "meaning": "شناسه یکتای تراکنش خرید",
      "data_type": "integer",
      "operations": "شناسایی هر خرید به طور مجزا"
    },
    {
      "table_name": "Purchases",
      "column_name": "CustomerID",
      "meaning": "شناسه مشتری که خرید را انجام داده (کلید خارجی)",
      "data_type": "integer",
      "operations": "ارتباط با جدول مشتریان برای شناسایی خریدار"
    },
    {
      "table_name": "Purchases",
      "column_name": "ProductID",
      "meaning": "شناسه محصول خریداری شده (کلید خارجی)",
      "data_type": "integer",
      "operations": "ارتباط با جدول محصولات برای شناسایی کالای خریداری شده"
    },
    {
      "table_name": "Purchases",
      "column_name": "PurchaseDate",
      "meaning": "تاریخ انجام خرید",
      "data_type": "date",
      "operations": "فیلتر کردن خریدها بر اساس بازه زمانی مانند ماه، سال یا روز گذشته"
    },
    {
      "table_name": "Purchases",
      "column_name": "PurchaseAmount",
      "meaning": "مبلغ پرداختی خرید به تومان",
      "data_type": "decimal",
      "operations": "محاسبه مجموع، میانگین و فیلتر کردن خریدها بر اساس مبلغ"
    },
    {
      "table_name": "Purchases",
      "column_name": "Quantity",
      "meaning": "تعداد کالای خریداری شده",
      "data_type": "integer",
      "operations": "محاسبه تعداد کل فروش و میانگین تعداد خرید"
    },
    {
      "table_name": "Orders",
      "column_name": "OrderID",
      "meaning": "شناسه یکتای سفارش",
      "data_type": "integer",
      "operations": "شناسایی هر سفارش به طور مجزا"
    },
    {
      "table_name": "Orders",
      "column_name": "CustomerID",
      "meaning": "شناسه مشتری ثبت‌کننده سفارش (کلید خارجی)",
      "data_type": "integer",
      "operations": "ارتباط با جدول مشتریان"
    },
    {
      "table_name": "Orders",
      "column_name": "OrderDate",
      "meaning": "تاریخ ثبت سفارش",
      "data_type": "date",
      "operations": "فیلتر و مرتب‌سازی سفارشات بر اساس تاریخ"
    },
    {
      "table_name": "Orders",
      "column_name": "Status",
      "meaning": "وضعیت سفارش مانند در انتظار، ارسال شده، تحویل داده شده",
      "data_type": "varchar",
      "operations": "فیلتر کردن سفارشات بر اساس وضعیت"
    },
    {
      "table_name": "Orders",
      "column_name": "TotalAmount",
      "meaning": "مبلغ کل سفارش",
      "data_type": "decimal",
      "operations": "محاسبه و فیلتر سفارشات بر اساس مبلغ"
    }
  ],
  "relations": [
    {
      "source_table": "Purchases",
      "source_column": "CustomerID",
      "target_table": "Customers",
      "target_column": "CustomerID",
      "relationship_type": "many-to-one",
      "join_purpose": "connecting each purchase to its customer for identifying who made the purchase"
    },
    {
      "source_table": "Purchases",
      "source_column": "ProductID",
      "target_table": "Products",
      "target_column": "ProductID",
      "relationship_type": "many-to-one",
      "join_purpose": "connecting each purchase to the product that was bought"
    },
    {
      "source_table": "Orders",
      "source_column": "CustomerID",
      "target_table": "Customers",
      "target_column": "CustomerID",
      "relationship_type": "many-to-one",
      "join_purpose": "connecting each order to the customer who placed it"
    }
  ]
}
